mudatasets/__init__.py
mudatasets/core.py
mudatasets/utils.py
mudatasets/datasets/__init__.py
mudatasets/datasets/brain3k_multiome.py
mudatasets/datasets/brain9k_multiome.py
mudatasets/datasets/pbmc10k_multiome.py
mudatasets/datasets/pbmc3k_multiome.py
mudatasets/datasets/pbmc5k_citeseq.py
mudatasets-0.0.2.dist-info/WHEEL
mudatasets-0.0.2.dist-info/METADATA
mudatasets-0.0.2.dist-info/RECORD
