Metadata-Version: 2.1
Name: mudatasets
Version: 0.0.2
Summary: Multimodal Datasets in MuData format
Home-page: https://github.com/PMBio/mudatasets
Author: Danila Bredikhin
Author-email: danila.bredikhin@embl.de
Requires-Python: >= 3.7
Classifier: Programming Language :: Python :: 3
Classifier: License :: OSI Approved :: BSD License
Classifier: Operating System :: OS Independent
Classifier: Development Status :: 3 - Alpha
Classifier: Topic :: Scientific/Engineering :: Bio-Informatics
Classifier: Intended Audience :: Science/Research
Requires-Dist: mudata
Requires-Dist: tqdm
Requires-Dist: requests
Requires-Dist: muon
Requires-Dist: sphinx >= 4.0 ; extra == "docs"
Requires-Dist: sphinx-rtd-theme ; extra == "docs"
Requires-Dist: readthedocs-sphinx-search ; extra == "docs"
Requires-Dist: nbsphinx ; extra == "docs"
Requires-Dist: sphinx_automodapi ; extra == "docs"
Requires-Dist: insegel ; extra == "docs"
Requires-Dist: muon ; extra == "muon"
Project-URL: Documentation, https://mudatasets.readthedocs.io/en/latest/
Provides-Extra: docs
Provides-Extra: muon
